[{"Id":"00000000-0000-0000-0000-000000000000","Title":"ghfghyghjuy gfghj","Content":"<p>,gfjvgmnhgi;yvbbbbbbbudf</p>\r\n","Link":"ghfghyghjuy-gfghj.html"},{"Id":"00000000-0000-0000-0000-000000000000","Title":"Text Editor","Content":"<h3>Text Editor</h3>\r\n","Link":"Text-Editor.html"},{"Id":"00000000-0000-0000-0000-000000000000","Title":"Text Editor","Content":"<p>sdrfe45t<strong><em>h6y6576t8j5</em></strong></p>\r\n","Link":"Text-Editor.html"},{"Id":"00000000-0000-0000-0000-000000000000","Title":"Text Editor","Content":"<h2 style=\"font-style:italic;\">&lt;a href=&quot;data:text/html;charset=utf-8;base64,@ViewB<em>ag.EncodedHtmlContent&quot; target=&quot;_blank&quot;&gt;</em><strong>@ViewBag.HtmlFileName&lt;/a&gt;</strong><br />\r\n&nbsp;</h2>\r\n","Link":"Text-Editor.html"},{"Id":"00000000-0000-0000-0000-000000000000","Title":"Text Editor","Content":"<p>&lt;a h<strong>ref=&quot;data:text/html;charset=utf-8;base64,@ViewBag.EncodedHtmlContent&quot; target=&quot;_blank&quot;&gt;@ViewBag.HtmlFileNam</strong>e&lt;/a&gt;<br />\r\n&nbsp;</p>\r\n","Link":"Text-Editor.html"},{"Id":"edfa03b1-02ec-419f-9893-b84b18ee7746","Title":"simran verma","Content":"<p>rbfrvtktgegtrhvgnhjghfdughu</p>\r\n","Link":"simran-verma.html"},{"Id":"b943c7ab-4d9c-4607-a620-4e6deebc1485","Title":"ggfh hjju","Content":"<p>gfh678j689k87oiu8o</p>\r\n","Link":"ggfh-hjju.html"},{"Id":"e5d0274b-7865-475d-b6b9-25bba313576f","Title":"ggfh hjju","Content":"<p>yuj8i9mo9p9</p>\r\n","Link":"ggfh-hjju.html"},{"Id":"00cdeb1e-0a31-4779-9ac0-c4815037b63b","Title":"ggfh hjju","Content":"<p>b7u76i78m89o8,py7tgvgbvc bcgtfd</p>\r\n","Link":"ggfh-hjju.html"},{"Id":"b442ec72-d829-4ab4-80fe-1eb122126dca","Title":"ggfh hjju","Content":"<p>efrrfggt5tmltriuitgtryibujyotf4rwwrurdhrtgu</p>\r\n","Link":"ggfh-hjju.html"},{"Id":"6cfee9e4-0c20-4cb3-9f71-459ae8d7691d","Title":"Text Editor","Content":"<p>rfgdukvtjgnyuuifbyh9</p>\r\n","Link":"Text-Editor.html"},{"Id":"ee0c8f97-0499-4527-97a5-6c0216b2407b","Title":"ggfh hjju","Content":"<p>76h8i889pl[990jhgtgfgh76ygr</p>\r\n","Link":"ggfh-hjju.html"},{"Id":"e65b8c6f-36fc-4cbf-bbb0-0ce1a9a5f71d","Title":"ggfh hjju","Content":"<p>b vvg bjmiikoijkihikhjgcfx</p>\r\n","Link":"ggfh-hjju.html"},{"Id":"8b6dcffc-2aab-40e2-9a3b-e00e9a908df0","Title":"Text Editor","Content":"<p>trgy7u yimjoilp[&#39;poferfdscxefdewsewfr</p>\r\n","Link":"Text-Editor.html"},{"Id":"f218544d-3573-4089-95e6-fdde6b1637ce","Title":"Text Editor","Content":"<p>DeleteArticleById(id);</p>\r\n","Link":"Text-Editor.html"},{"Id":"b24bfbd0-3426-43b9-b5b9-2671eacf0309","Title":"ggfh hjju","Content":"<p>7ujjjiklio;.9ppojkmhgjht7u7y6tiuik7i87</p>\r\n","Link":"ggfh-hjju.html"},{"Id":"07589ca2-7329-484b-ad18-31df70189bcf","Title":"ggfh hjju","Content":"<p>rtyrjhytut76</p>\r\n","Link":"ggfh-hjju.html"},{"Id":"b9dd8ced-d068-4e7c-ad60-5ba6f1ef3c6e","Title":"ghtryrty","Content":"<p>grtdy6hr7yujuyi6iok76</p>\r\n","Link":"ghtryrty.html"},{"Id":"61b27389-3d98-4614-9864-d888b8255204","Title":"ghfghyghjuy gfghj","Content":"<p>tyujyikloiu</p>\r\n","Link":"ghfghyghjuy-gfghj.html"}]